dooflask_cli/__init__.py
dooflask_cli/dooflask_cli.py
dooflask_cli-0.1a3.dist-info/METADATA
dooflask_cli-0.1a3.dist-info/WHEEL
dooflask_cli-0.1a3.dist-info/entry_points.txt
dooflask_cli-0.1a3.dist-info/top_level.txt
dooflask_cli-0.1a3.dist-info/RECORD
