Metadata-Version: 2.1
Name: dooflask-cli
Version: 0.1a3
Summary: Command CLI for dooflask framework
Home-page: https://github.com/arissupriy/dooflask
Author: Aris Supriyanto
Author-email: arissy96@gmail.com
License: MIT
Platform: UNKNOWN
Requires-Dist: requests
